{"OutputFileHashSum":"A2991CA6CF0C73A26F06844728CBFB2BD11DE5044B922805E3922868DEC83B1A","Converted":true,"OutputModifyDate":"2020-05-13T14:10:29.5366605Z","Metadatas":[{"CategoryName":"VuGen.Replay","Offset":561,"Length":21,"TypeId":1},{"CategoryName":"VuGen.Replay","Offset":687,"Length":83,"TypeId":2},{"CategoryName":"VuGen.Replay","Offset":1657,"Length":66,"TypeId":2},{"CategoryName":"VuGen.Replay","Offset":3169,"Length":124,"TypeId":2},{"CategoryName":"VuGen.Replay","Offset":3339,"Length":62,"TypeId":2},{"CategoryName":"VuGen.Replay","Offset":5977,"Length":120,"TypeId":2},{"CategoryName":"VuGen.Replay","Offset":6143,"Length":70,"TypeId":2},{"CategoryName":"VuGen.Replay","Offset":8263,"Length":129,"TypeId":2},{"CategoryName":"VuGen.Replay","Offset":8439,"Length":69,"TypeId":2},{"CategoryName":"VuGen.Replay","Offset":9473,"Length":127,"TypeId":2},{"CategoryName":"VuGen.Replay","Offset":9647,"Length":71,"TypeId":2},{"CategoryName":"VuGen.Replay","Offset":10366,"Length":129,"TypeId":2},{"CategoryName":"VuGen.Replay","Offset":10542,"Length":64,"TypeId":2},{"CategoryName":"VuGen.Replay","Offset":12241,"Length":122,"TypeId":2},{"CategoryName":"VuGen.Replay","Offset":12365,"Length":164,"TypeId":2},{"CategoryName":"VuGen.Replay","Offset":12554,"Length":19,"TypeId":1}],"MetadataTypes":[{"CategoryName":"VuGen.Replay","MetadataTypeName":"HP.LR.Vugen.Iteration","Id":1},{"CategoryName":"VuGen.Replay","MetadataTypeName":"HP.LR.Vugen.NotifyTransaction","Id":2}]}