[
    {
        "actionName": "Action",
        "steps": [
            {
                "stepId": "STEP274",
                "stepName": "Url: WebTours",
                "infFile": "t1.inf",
                "time": 1589471324660
            },
            {
                "stepId": "STEP275",
                "stepName": "Submit Data: login.pl",
                "infFile": "t2.inf",
                "time": 1589471325415
            },
            {
                "stepId": "STEP276",
                "stepName": "Url: Search Flights Button",
                "infFile": "t3.inf",
                "time": 1589471326061
            },
            {
                "stepId": "STEP277",
                "stepName": "Submit Data: reservations.pl",
                "infFile": "t5.inf",
                "time": 1589471326424
            },
            {
                "stepId": "STEP278",
                "stepName": "Submit Data: reservations.pl_2",
                "infFile": "t6.inf",
                "time": 1589471326860
            },
            {
                "stepId": "STEP279",
                "stepName": "Submit Data: reservations.pl_3",
                "infFile": "t7.inf",
                "time": 1589471327362
            },
            {
                "stepId": "STEP280",
                "stepName": "Url: SignOff Button",
                "infFile": "t8.inf",
                "time": 1589471327787
            }
        ],
        "transactions": [
            {
                "transactionName": "transaction_open_link",
                "rawStartTime": 1589471324068,
                "rawEndTime": 1589471324662,
                "thinkTime": 0.0,
                "wastedTime": 0.359790563583374
            },
            {
                "transactionName": "transaction_login",
                "rawStartTime": 1589471324667,
                "rawEndTime": 1589471325417,
                "thinkTime": 0.0,
                "wastedTime": 0.39539647102355959
            },
            {
                "transactionName": "transaction_click_flights",
                "rawStartTime": 1589471325421,
                "rawEndTime": 1589471326063,
                "thinkTime": 0.0,
                "wastedTime": 0.33454370498657229
            },
            {
                "transactionName": "transaction_find_flight",
                "rawStartTime": 1589471326067,
                "rawEndTime": 1589471326426,
                "thinkTime": 0.0,
                "wastedTime": 0.2159736156463623
            },
            {
                "transactionName": "transaction_select_flight",
                "rawStartTime": 1589471326430,
                "rawEndTime": 1589471326862,
                "thinkTime": 0.0,
                "wastedTime": 0.27006983757019045
            },
            {
                "transactionName": "transaction_payment_details",
                "rawStartTime": 1589471326866,
                "rawEndTime": 1589471327364,
                "thinkTime": 0.0,
                "wastedTime": 0.2725832462310791
            },
            {
                "transactionName": "transaction_logout",
                "rawStartTime": 1589471327368,
                "rawEndTime": 1589471327789,
                "thinkTime": 0.0,
                "wastedTime": 0.23438405990600587
            },
            {
                "transactionName": "1_buy_ticket_transaction",
                "rawStartTime": 1589471324047,
                "rawEndTime": 1589471327791,
                "thinkTime": 0.0,
                "wastedTime": 2.0827414989471437
            }
        ]
    }
]